matrix_transform/__init__.py
matrix_transform/geometric.py
matrix_transform/utils.py
matrix_transform-1.0.2.dist-info/LICENSE
matrix_transform-1.0.2.dist-info/WHEEL
matrix_transform-1.0.2.dist-info/METADATA
matrix_transform-1.0.2.dist-info/RECORD
